[
  {
    "obj_id": "32",
    "obj_type": "Truck",
    "psr": {
      "position": {
        "x": 28.648024240689892,
        "y": 0.5196682963855892,
        "z": 1.2851826896992986
      },
      "rotation": {
        "x": 0,
        "y": 0,
        "z": 0.07611461327750513
      },
      "scale": {
        "x": 5.584177194597359,
        "y": 2.65996059718211,
        "z": 4.612901692958987
      }
    }
  },
  {
    "obj_id": "87",
    "obj_type": "Car",
    "psr": {
      "position": {
        "x": -10.58680933363678,
        "y": -1.1813078478404009,
        "z": -1.2194136234737945
      },
      "rotation": {
        "x": 0,
        "y": 0,
        "z": 0.0024684849518318477
      },
      "scale": {
        "x": 4.4841404206822695,
        "y": 2.19600272420697,
        "z": 1.735521955276603
      }
    }
  }
]