[
  {
    "obj_id": "32",
    "obj_type": "Truck",
    "psr": {
      "position": {
        "x": 27.11700144212591,
        "y": 0.24005001681871363,
        "z": 1.5230079426540608
      },
      "rotation": {
        "x": 0,
        "y": 0,
        "z": -0.0313478211253524
      },
      "scale": {
        "x": 5.584177194597359,
        "y": 2.65996059718211,
        "z": 4.612901692958987
      }
    }
  },
  {
    "annotator": "i",
    "obj_id": "87",
    "obj_type": "Car",
    "psr": {
      "position": {
        "x": -11.69799169936914,
        "y": -0.7792151360627031,
        "z": -1.3010837845391068
      },
      "rotation": {
        "x": 0,
        "y": 0,
        "z": 0.053207850320559316
      },
      "scale": {
        "x": 4.4841404206822695,
        "y": 2.19600272420697,
        "z": 1.735521955276603
      }
    }
  }
]