[
  {
    "obj_id": "32",
    "obj_type": "Truck",
    "psr": {
      "position": {
        "x": 26.11268193660908,
        "y": -0.16695387044910603,
        "z": 1.1408617814904591
      },
      "rotation": {
        "x": 0,
        "y": 0,
        "z": 0.023833155982020925
      },
      "scale": {
        "x": 5.584177194597359,
        "y": 2.65996059718211,
        "z": 4.612901692958987
      }
    }
  },
  {
    "obj_id": "33",
    "obj_type": "Van",
    "psr": {
      "position": {
        "x": -3.8217261646932457,
        "y": 3.358987307919051,
        "z": -0.8064646399259693
      },
      "rotation": {
        "x": 0,
        "y": 0,
        "z": -0.020533622004243177
      },
      "scale": {
        "x": 5.005807618262742,
        "y": 2.245247420597348,
        "z": 1.9065776434086512
      }
    }
  },
  {
    "obj_id": "87",
    "obj_type": "Car",
    "psr": {
      "position": {
        "x": -15.301805820839945,
        "y": -0.4254790709410372,
        "z": -1.4001191060461142
      },
      "rotation": {
        "x": 0,
        "y": 0,
        "z": 0.006824502689296774
      },
      "scale": {
        "x": 4.4841404206822695,
        "y": 2.19600272420697,
        "z": 1.735521955276603
      }
    }
  }
]