[
  {
    "obj_id": "37",
    "obj_type": "Car",
    "psr": {
      "position": {
        "x": 8.34366496442135,
        "y": 0.019620539864912905,
        "z": -0.6498743386271483
      },
      "rotation": {
        "x": 0,
        "y": 0,
        "z": 0.020587897350910284
      },
      "scale": {
        "x": 4.44378593849864,
        "y": 2.0549206213904885,
        "z": 1.4402231971196127
      }
    }
  },
  {
    "obj_id": "39",
    "obj_type": "Truck",
    "psr": {
      "position": {
        "x": 9.658387116366612,
        "y": 10.328667133677161,
        "z": -0.21893297844692383
      },
      "rotation": {
        "x": 0,
        "y": 0,
        "z": -2.683129526350677
      },
      "scale": {
        "x": 6.957991372510753,
        "y": 2.269697014435682,
        "z": 2.187476873397827
      }
    }
  },
  {
    "obj_id": "87",
    "obj_type": "Car",
    "psr": {
      "position": {
        "x": -7.09553132739984,
        "y": -0.27983186855453823,
        "z": -0.9217583708591877
      },
      "rotation": {
        "x": 0,
        "y": 0,
        "z": 0.027815421745906035
      },
      "scale": {
        "x": 4.4841404206822695,
        "y": 2.19600272420697,
        "z": 1.735521955276603
      }
    }
  }
]