[
  {
    "obj_id": "48",
    "obj_type": "Car",
    "psr": {
      "position": {
        "x": -4.2987103864488745,
        "y": 6.488740289905763,
        "z": -1.2060880555071507
      },
      "rotation": {
        "x": 0,
        "y": 0,
        "z": 3.115412714809878
      },
      "scale": {
        "x": 4.859737123040862,
        "y": 2.3244116169248388,
        "z": 2.0398363769054413
      }
    }
  },
  {
    "obj_id": "89",
    "obj_type": "Car",
    "psr": {
      "position": {
        "x": 1.3425912171305754,
        "y": -3.5719593501221425,
        "z": -0.8727323321630781
      },
      "rotation": {
        "x": 0,
        "y": 0,
        "z": -0.14584102135436963
      },
      "scale": {
        "x": 4.7978000689720925,
        "y": 2.206447515296878,
        "z": 1.5507385389512356
      }
    }
  }
]