[
  {
    "obj_id": "32",
    "obj_type": "Truck",
    "psr": {
      "position": {
        "x": 27.243096125605007,
        "y": 0.27718535891153806,
        "z": 1.5183742889565681
      },
      "rotation": {
        "x": 0,
        "y": 0,
        "z": -0.026179938779915105
      },
      "scale": {
        "x": 5.584177194597359,
        "y": 2.65996059718211,
        "z": 4.612901692958987
      }
    }
  },
  {
    "obj_id": "34",
    "obj_type": "Car",
    "psr": {
      "position": {
        "x": 9.95445578984436,
        "y": 3.9458373668039712,
        "z": -0.5618856310552969
      },
      "rotation": {
        "x": 0,
        "y": 0,
        "z": -0.012495659254089457
      },
      "scale": {
        "x": 4.100871097813187,
        "y": 2.1773357941994003,
        "z": 1.7256458873139149
      }
    }
  },
  {
    "obj_id": "87",
    "obj_type": "Car",
    "psr": {
      "position": {
        "x": -12.50053365984786,
        "y": -0.24558007983796415,
        "z": -1.2649718970956
      },
      "rotation": {
        "x": 0,
        "y": 0,
        "z": -0.012923276073995323
      },
      "scale": {
        "x": 4.4841404206822695,
        "y": 2.19600272420697,
        "z": 1.735521955276603
      }
    }
  }
]