[
  {
    "obj_id": "32",
    "obj_type": "Truck",
    "psr": {
      "position": {
        "x": 27.18613094290049,
        "y": 0.2398065566776495,
        "z": 1.5140933130698144
      },
      "rotation": {
        "x": 0,
        "y": 0,
        "z": -0.026179938779915105
      },
      "scale": {
        "x": 5.584177194597359,
        "y": 2.65996059718211,
        "z": 4.612901692958987
      }
    }
  },
  {
    "obj_id": "34",
    "obj_type": "Car",
    "psr": {
      "position": {
        "x": 11.43238262065779,
        "y": 3.917760746971908,
        "z": -0.5035292502931785
      },
      "rotation": {
        "x": 0,
        "y": 0,
        "z": -0.016405453404325355
      },
      "scale": {
        "x": 4.100871097813187,
        "y": 2.1773357941994003,
        "z": 1.7256458873139149
      }
    }
  },
  {
    "obj_id": "87",
    "obj_type": "Car",
    "psr": {
      "position": {
        "x": -12.524182505940189,
        "y": -0.2554390890891227,
        "z": -1.27463357509814
      },
      "rotation": {
        "x": 0,
        "y": 0,
        "z": -0.01734216364263524
      },
      "scale": {
        "x": 4.4841404206822695,
        "y": 2.19600272420697,
        "z": 1.735521955276603
      }
    }
  }
]