[
  {
    "obj_id": "46",
    "obj_type": "Car",
    "psr": {
      "position": {
        "x": -3.7253289674818006,
        "y": 6.412240752320031,
        "z": -1.4308149433798258
      },
      "rotation": {
        "x": 0,
        "y": 0,
        "z": 3.112133406752077
      },
      "scale": {
        "x": 4.358255814599184,
        "y": 2.1338016567838114,
        "z": 1.544639378786087
      }
    }
  },
  {
    "obj_id": "89",
    "obj_type": "Car",
    "psr": {
      "position": {
        "x": -9.852078977582096,
        "y": 0.3439106242608432,
        "z": -1.3567464134546614
      },
      "rotation": {
        "x": 0,
        "y": 0,
        "z": -0.04683722737950174
      },
      "scale": {
        "x": 4.933897327997296,
        "y": 2.0288595984999542,
        "z": 1.3171941637992859
      }
    }
  }
]