[
  {
    "obj_id": "32",
    "obj_type": "Truck",
    "psr": {
      "position": {
        "x": 26.77534133028803,
        "y": 0.674804365467935,
        "z": 1.1625058557637096
      },
      "rotation": {
        "x": 0,
        "y": 0,
        "z": 0.004694368104970856
      },
      "scale": {
        "x": 5.584177194597359,
        "y": 2.65996059718211,
        "z": 4.612901692958987
      }
    }
  },
  {
    "obj_id": "34",
    "obj_type": "Car",
    "psr": {
      "position": {
        "x": -8.406592250041285,
        "y": 3.9012704716856206,
        "z": -1.4258492843145731
      },
      "rotation": {
        "x": 0,
        "y": 0,
        "z": 0.026179938779914928
      },
      "scale": {
        "x": 4.100871097813187,
        "y": 2.1773357941994003,
        "z": 1.7256458873139149
      }
    }
  },
  {
    "obj_id": "87",
    "obj_type": "Car",
    "psr": {
      "position": {
        "x": -12.267430322013752,
        "y": -0.12106631002097856,
        "z": -1.3137639645193353
      },
      "rotation": {
        "x": 0,
        "y": 0,
        "z": -0.0028609599583200415
      },
      "scale": {
        "x": 4.4841404206822695,
        "y": 2.19600272420697,
        "z": 1.735521955276603
      }
    }
  }
]