[
  {
    "obj_id": "1",
    "obj_type": "Truck",
    "psr": {
      "position": {
        "x": -1.0837373503637764,
        "y": -14.946118472186754,
        "z": -0.8505813152487597
      },
      "rotation": {
        "x": 0,
        "y": 0,
        "z": -0.11303905688757754
      },
      "scale": {
        "x": 5.691709330337483,
        "y": 2.639079666595305,
        "z": 2.1748800980858505
      }
    }
  },
  {
    "obj_id": "2",
    "obj_type": "Car",
    "psr": {
      "position": {
        "x": -1.1185231860029035,
        "y": -9.945130786768459,
        "z": -1.0230379046190066
      },
      "rotation": {
        "x": 0,
        "y": 0,
        "z": -0.1023680044197146
      },
      "scale": {
        "x": 4.859945988482682,
        "y": 2.1671739751424974,
        "z": 1.5183730125427246
      }
    }
  }
]