[
  {
    "obj_id": "32",
    "obj_type": "Truck",
    "psr": {
      "position": {
        "x": 27.166362385472894,
        "y": 0.4673849028049517,
        "z": 1.2047624003581778
      },
      "rotation": {
        "x": 0,
        "y": 0,
        "z": 0.003108833341604597
      },
      "scale": {
        "x": 5.584177194597359,
        "y": 2.65996059718211,
        "z": 4.612901692958987
      }
    }
  },
  {
    "obj_id": "34",
    "obj_type": "Car",
    "psr": {
      "position": {
        "x": -2.681297430957784,
        "y": 3.9803856965754676,
        "z": -1.2025502604083909
      },
      "rotation": {
        "x": 0,
        "y": 0,
        "z": 0.016183411376643433
      },
      "scale": {
        "x": 4.100871097813187,
        "y": 2.1773357941994003,
        "z": 1.7256458873139149
      }
    }
  },
  {
    "obj_id": "87",
    "obj_type": "Car",
    "psr": {
      "position": {
        "x": -12.29353845354126,
        "y": -0.15626114683436754,
        "z": -1.2778349747905708
      },
      "rotation": {
        "x": 0,
        "y": 0,
        "z": 0.000961113350315774
      },
      "scale": {
        "x": 4.4841404206822695,
        "y": 2.19600272420697,
        "z": 1.735521955276603
      }
    }
  }
]