[
  {
    "obj_id": "51",
    "obj_type": "Car",
    "psr": {
      "position": {
        "x": -11.398840429854317,
        "y": 7.638778542421278,
        "z": -1.6776695578869925
      },
      "rotation": {
        "x": 0,
        "y": 0,
        "z": 3.115412714809878
      },
      "scale": {
        "x": 4.567302679385761,
        "y": 2.2006022178148177,
        "z": 1.5977864861488342
      }
    }
  },
  {
    "obj_id": "52",
    "obj_type": "Car",
    "psr": {
      "position": {
        "x": 7.516491754980962,
        "y": 5.805620187400564,
        "z": -1.0328941270709038
      },
      "rotation": {
        "x": 0,
        "y": 0,
        "z": 3.089819521233036
      },
      "scale": {
        "x": 5.008373329283968,
        "y": 1.8304785397834724,
        "z": 1.4963999837636948
      }
    }
  }
]