[
  {
    "obj_id": "32",
    "obj_type": "Truck",
    "psr": {
      "position": {
        "x": 27.811063807014307,
        "y": -0.23282396168542618,
        "z": 1.59260783321503
      },
      "rotation": {
        "x": 0,
        "y": 0,
        "z": -0.04553236673378214
      },
      "scale": {
        "x": 5.584177194597359,
        "y": 2.65996059718211,
        "z": 4.612901692958987
      }
    }
  },
  {
    "annotator": "i",
    "obj_id": "87",
    "obj_type": "Car",
    "psr": {
      "position": {
        "x": -11.50935968792055,
        "y": -0.6213882784977613,
        "z": -1.2952895497297352
      },
      "rotation": {
        "x": -0.0015545803302156932,
        "y": -4.7061233378331575e-05,
        "z": 0.0379076264729798
      },
      "scale": {
        "x": 4.4841404206822695,
        "y": 2.19600272420697,
        "z": 1.735521955276603
      }
    }
  }
]