[
  {
    "obj_id": "48",
    "obj_type": "Car",
    "psr": {
      "position": {
        "x": -7.350470308463628,
        "y": 6.647316729650356,
        "z": -1.276316074537657
      },
      "rotation": {
        "x": 0,
        "y": 0,
        "z": 3.115412714809878
      },
      "scale": {
        "x": 4.859737123040862,
        "y": 2.3244116169248388,
        "z": 2.0398363769054413
      }
    }
  },
  {
    "obj_id": "89",
    "obj_type": "Car",
    "psr": {
      "position": {
        "x": 2.6123853100070846,
        "y": -3.7290093903563957,
        "z": -0.8483915664912131
      },
      "rotation": {
        "x": 0,
        "y": 0,
        "z": -0.11435168762069249
      },
      "scale": {
        "x": 4.7978000689720925,
        "y": 2.206447515296878,
        "z": 1.5507385389512356
      }
    }
  }
]