[
  {
    "obj_id": "31",
    "obj_type": "Car",
    "psr": {
      "position": {
        "x": -0.6681723503303223,
        "y": 2.822315056570177,
        "z": -0.8851031266057792
      },
      "rotation": {
        "x": 0,
        "y": 0,
        "z": 0.016361764471706293
      },
      "scale": {
        "x": 5.864029777128726,
        "y": 1.9712123153682417,
        "z": 1.6243207179923926
      }
    }
  },
  {
    "obj_id": "32",
    "obj_type": "Truck",
    "psr": {
      "position": {
        "x": 26.56236559473564,
        "y": 0.5417538968480358,
        "z": 1.3196574747562413
      },
      "rotation": {
        "x": 0,
        "y": 0,
        "z": 0.04990476499942452
      },
      "scale": {
        "x": 5.584177194597359,
        "y": 2.65996059718211,
        "z": 4.612901692958987
      }
    }
  },
  {
    "obj_id": "87",
    "obj_type": "Car",
    "psr": {
      "position": {
        "x": -12.60138019522064,
        "y": -1.3744397730526134,
        "z": -1.2687161483696818
      },
      "rotation": {
        "x": 0,
        "y": 0,
        "z": -0.005252026045234991
      },
      "scale": {
        "x": 4.4841404206822695,
        "y": 2.19600272420697,
        "z": 1.735521955276603
      }
    }
  }
]