[
  {
    "obj_id": "23",
    "obj_type": "Car",
    "psr": {
      "position": {
        "x": 10.404084242287809,
        "y": 3.3234083226411713,
        "z": -0.7315944042793932
      },
      "rotation": {
        "x": 0,
        "y": 0,
        "z": -0.017338635821802173
      },
      "scale": {
        "x": 4.482931594947052,
        "y": 2.042702966411349,
        "z": 1.6281104868666287
      }
    }
  },
  {
    "obj_id": "72",
    "obj_type": "Truck",
    "psr": {
      "position": {
        "x": 38.07967349981067,
        "y": 28.766424380398284,
        "z": 0.10852810808327443
      },
      "rotation": {
        "x": 0,
        "y": 0,
        "z": 3.1006133007391052
      },
      "scale": {
        "x": 6.133693747988096,
        "y": 3.9538771011700433,
        "z": 2.796790361404419
      }
    }
  }
]