[
  {
    "obj_id": "48",
    "obj_type": "Car",
    "psr": {
      "position": {
        "x": -1.3454781010859733,
        "y": 6.359873271725519,
        "z": -1.1193841844797134
      },
      "rotation": {
        "x": 0,
        "y": 0,
        "z": 3.114014809865055
      },
      "scale": {
        "x": 4.859737123040862,
        "y": 2.3244116169248388,
        "z": 2.0398363769054413
      }
    }
  },
  {
    "obj_id": "89",
    "obj_type": "Car",
    "psr": {
      "position": {
        "x": 0.07279712425327552,
        "y": -3.414909309888071,
        "z": -0.8970730978349432
      },
      "rotation": {
        "x": 0,
        "y": 0,
        "z": -0.17733035508804676
      },
      "scale": {
        "x": 4.7978000689720925,
        "y": 2.206447515296878,
        "z": 1.5507385389512356
      }
    }
  }
]