[
  {
    "obj_id": "37",
    "obj_type": "Car",
    "psr": {
      "position": {
        "x": 9.529772214659715,
        "y": 0.030166920329975255,
        "z": -0.6269214714824503
      },
      "rotation": {
        "x": 0,
        "y": 0,
        "z": 0.011131072401340647
      },
      "scale": {
        "x": 4.44378593849864,
        "y": 2.0549206213904885,
        "z": 1.4402231971196127
      }
    }
  },
  {
    "obj_id": "38",
    "obj_type": "Truck",
    "psr": {
      "position": {
        "x": -2.654238059098134,
        "y": 7.1629985489817045,
        "z": -0.7976339691664525
      },
      "rotation": {
        "x": 0,
        "y": 0,
        "z": -2.996059518938904
      },
      "scale": {
        "x": 5.779963955335753,
        "y": 2.7551803838411084,
        "z": 2.0390522480010986
      }
    }
  },
  {
    "obj_id": "87",
    "obj_type": "Car",
    "psr": {
      "position": {
        "x": -9.532728340271206,
        "y": -0.32622523326244846,
        "z": -1.217315515164751
      },
      "rotation": {
        "x": 0,
        "y": 0,
        "z": 0.029103380331938135
      },
      "scale": {
        "x": 4.4841404206822695,
        "y": 2.19600272420697,
        "z": 1.735521955276603
      }
    }
  }
]